sievelib/__init__.py
sievelib/commands.py
sievelib/digest_md5.py
sievelib/factory.py
sievelib/managesieve.py
sievelib/parser.py
sievelib/tools.py
sievelib/tests/__init__.py
sievelib/tests/test_factory.py
sievelib/tests/test_managesieve.py
sievelib/tests/test_parser.py
sievelib/tests/files/utf8_sieve.txt
sievelib-1.2.1.dist-info/COPYING
sievelib-1.2.1.dist-info/METADATA
sievelib-1.2.1.dist-info/WHEEL
sievelib-1.2.1.dist-info/top_level.txt
sievelib-1.2.1.dist-info/RECORD
