Metadata-Version: 2.1
Name: sievelib
Version: 1.2.1
Summary: Client-side SIEVE library
Home-page: https://github.com/tonioo/sievelib
Author: Antoine Nguyen
Author-email: tonio@ngyn.org
License: MIT
Keywords: sieve,managesieve,parser,client
Platform: UNKNOWN
Classifier: Programming Language :: Python
Classifier: Development Status :: 4 - Beta
Classifier: Intended Audience :: Developers
Classifier: License :: OSI Approved :: MIT License
Classifier: Operating System :: OS Independent
Classifier: Topic :: Software Development :: Libraries :: Python Modules
Classifier: Topic :: Communications :: Email :: Filters
